[
    {"date" : "Jan 2016", "click": -1.74, "arc": -1.04},
    {"date" : "Feb 2016", "click": 0.74, "arc": 0.37},
    {"date" : "Mar 2016", "click": 1.02, "arc": 0.87},
    {"date" : "Apr 2016", "click": -0.09, "arc": 0.16},
    {"date" : "May 2016", "click": 0.73, "arc": 0.42},
    {"date" : "Jun 2016", "click": 1.79, "arc": 0.75},
    {"date" : "Jul 2016", "click": 3.57, "arc": 1.86},
    {"date" : "Aug 2016", "click": 1.53, "arc": 1.04},
    {"date" : "Sep 2016", "click": 0.39, "arc": 0.18},
    {"date" : "Oct 2016", "click": 1.24, "arc": 0.29},
    {"date" : "Nov 2016", "click": -1.23, "arc": -0.87},
    {"date" : "Dec 2016", "click": 1.74, "arc": 1.40},
    {"date" : "Jan 2017", "click": 0.67, "arc": 0.14},
    {"date" : "Feb 2017", "click": 1.55, "arc": 1.24},
    {"date" : "Mar 2017", "click": 0.32, "arc": 0.31},
    {"date" : "Apr 2017", "click": 0.41, "arc": 0.21},
    {"date" : "May 2017", "click": 1.88, "arc": 1.16},
    {"date" : "Jun 2017", "click": -1.09, "arc": -0.58},
    {"date" : "Jul 2017", "click": 0.57, "arc": 0.49},
    {"date" : "Aug 2017", "click": 1.00, "arc": 0.92},
    {"date" : "Sep 2017", "click": -0.88, "arc": -0.89},
    {"date" : "Oct 2017", "click": 1.41, "arc": 0.87},
    {"date" : "Nov 2017", "click": -0.52, "arc": -0.25},
    {"date" : "Dec 2017", "click": 1.29, "arc": 0.79},
    {"date" : "Jan 2018", "click": -0.67, "arc": -0.17},
    {"date" : "Feb 2018", "click": -0.78, "arc": -0.96},
    {"date" : "Mar 2018", "click": -1.77, "arc": -0.91},
    {"date" : "Apr 2018", "click": 2.54, "arc": 1.16},
    {"date" : "May 2018", "click": 1.51, "arc": 0.50},
    {"date" : "Jun 2018", "click": -0.44, "arc": -0.11},
    {"date" : "Jul 2018", "click": 1.00, "arc": 0.57},
    {"date" : "Aug 2018", "click": 0.32, "arc": 0.00},
    {"date" : "Sep 2018", "click": -0.79, "arc": -0.17},
    {"date" : "Oct 2018", "click": -2.25, "arc": -1.79},
    {"date" : "Nov 2018", "click": 0.45, "arc": -0.22},
    {"date" : "Dec 2018", "click": -2.54, "arc": -1.54}
]